onenuron/__init__.py
onenuron/perceptron.py
utils/__init__.py
utils/all_utils.py
percetron_pypi_sandeepjena7-0.0.4.dist-info/LICENSE
percetron_pypi_sandeepjena7-0.0.4.dist-info/METADATA
percetron_pypi_sandeepjena7-0.0.4.dist-info/WHEEL
percetron_pypi_sandeepjena7-0.0.4.dist-info/top_level.txt
percetron_pypi_sandeepjena7-0.0.4.dist-info/RECORD
