Metadata-Version: 2.1
Name: percetron-pypi-sandeepjena7
Version: 0.0.4
Summary: Its a implementation of percetron
Home-page: https://github.com/sandeepjena7/percetron_pypi
Author: sandeepjena7
Author-email: sandeepjena777@gmail.com
License: UNKNOWN
Project-URL: Bug Tracker, https://github.com/sandeepjena7/percetron_pypi/issues
Platform: UNKNOWN
Classifier: Programming Language :: Python :: 3
Classifier: License :: OSI Approved :: MIT License
Classifier: Operating System :: OS Independent
Requires-Python: >=3.8
License-File: LICENSE
Requires-Dist: numpy
Requires-Dist: tqdm
Requires-Dist: matplotlib
Requires-Dist: pandas
Requires-Dist: joblib
